add_confidence_and_coordinates/__init__.py
add_confidence_and_coordinates/openai_json_updater.py
add_confidence_and_coordinates/utils.py
tests/__init__.py
tests/test_json_updater.py
add_confidence_score_and_coordinates-1.0.4.dist-info/LICENSE
add_confidence_score_and_coordinates-1.0.4.dist-info/METADATA
add_confidence_score_and_coordinates-1.0.4.dist-info/WHEEL
add_confidence_score_and_coordinates-1.0.4.dist-info/top_level.txt
add_confidence_score_and_coordinates-1.0.4.dist-info/RECORD
